LICENSE
blankslate/__init__.py
blankslate/config/__init__.py
blankslate/config/constants.py
blankslate/config/paths.py
blankslate/generation/__init__.py
blankslate/generation/folder_generation.py
blankslate/generation/project_generation.py
blankslate/generation/template_rendering.py
blankslate/generation/templates/.gitignore.j2
blankslate/generation/templates/.nojekyll.j2
blankslate/generation/templates/.pre-commit-config.yaml.j2
blankslate/generation/templates/__init__.py.j2
blankslate/generation/templates/CHANGELOG.md.j2
blankslate/generation/templates/command_line.py.j2
blankslate/generation/templates/conf.py.j2
blankslate/generation/templates/constants.py.j2
blankslate/generation/templates/continuous_integration.yml.j2
blankslate/generation/templates/CONTRIBUTING.md.j2
blankslate/generation/templates/extensions.json.j2
blankslate/generation/templates/index.rst.j2
blankslate/generation/templates/LICENSE.j2
blankslate/generation/templates/main.py.j2
blankslate/generation/templates/make.bat.j2
blankslate/generation/templates/Makefile.j2
blankslate/generation/templates/paths.py.j2
blankslate/generation/templates/py.typed.j2
blankslate/generation/templates/pyproject.toml.j2
blankslate/generation/templates/README.md.j2
blankslate/generation/templates/release.sh.j2
blankslate/generation/templates/requirements-dev.txt.j2
blankslate/generation/templates/requirements.txt.j2
blankslate/generation/templates/setup_logging.py.j2
blankslate/generation/templates/test_main.py.j2
blankslate/generation/templates/todo_to_issue.yml.j2
blankslate/generation/templates/tox.ini.j2
blankslate/generation/templates/VERSION.j2
blankslate/interface/__init__.py
blankslate/interface/command_line.py
blankslate/logs/__init__.py
blankslate/logs/setup_logging.py
blankslate/main.py
blankslate/py.typed
blankslate/VERSION
blankslate_python-1.3.5.dist-info/entry_points.txt
blankslate_python-1.3.5.dist-info/LICENSE
blankslate_python-1.3.5.dist-info/METADATA
blankslate_python-1.3.5.dist-info/WHEEL
blankslate_python-1.3.5.dist-info/RECORD
