Metadata-Version: 2.1
Name: blankslate-python
Version: 1.3.5
Summary: A blank slate for Python projects
Home-page: https://github.com/unkokaeru/blankslate
License: MIT
Author: William Fayers
Author-email: wills@fayers.com
Requires-Python: >=3.8,<4.0
Classifier: License :: OSI Approved :: MIT License
Classifier: Programming Language :: Python :: 3
Classifier: Programming Language :: Python :: 3.8
Classifier: Programming Language :: Python :: 3.9
Classifier: Programming Language :: Python :: 3.10
Classifier: Programming Language :: Python :: 3.11
Classifier: Programming Language :: Python :: 3.12
Provides-Extra: dev
Provides-Extra: devlint
Provides-Extra: docs
Provides-Extra: lint
Provides-Extra: release
Provides-Extra: test
Provides-Extra: types
Requires-Dist: Jinja2 (>=3.0.0,<4.0.0)
Requires-Dist: rich (>=12.0.0,<13.0.0)
Project-URL: Repository, https://github.com/unkokaeru/blankslate
